image_titles/__init__.py
image_titles/image_titles.py
markdown_image_titles-0.1.0.dist-info/LICENSE
markdown_image_titles-0.1.0.dist-info/METADATA
markdown_image_titles-0.1.0.dist-info/WHEEL
markdown_image_titles-0.1.0.dist-info/top_level.txt
markdown_image_titles-0.1.0.dist-info/RECORD
